gdex_api_client/__init__.py
gdex_api_client/gdex_client.py
gdex_api_client-2.0.8.dist-info/licenses/LICENSE
gdex_api_client-2.0.8.dist-info/METADATA
gdex_api_client-2.0.8.dist-info/WHEEL
gdex_api_client-2.0.8.dist-info/entry_points.txt
gdex_api_client-2.0.8.dist-info/top_level.txt
gdex_api_client-2.0.8.dist-info/RECORD
