Metadata-Version: 2.4
Name: gdex-api-client
Version: 2.0.8
Summary: CLI and library for calling GDEX API
Author-email: GDEX data Help <datahelp@ucar.edu>
License-Expression: MIT
Project-URL: Homepage, https://gdex.ucar/edu
Keywords: API,Geoscience,GDEX
License-File: LICENSE
Requires-Dist: requests
Dynamic: license-file
